fastapi_otel_common/__init__.py
fastapi_otel_common/app.py
fastapi_otel_common/py.typed
fastapi_otel_common/core/__init__.py
fastapi_otel_common/core/config.py
fastapi_otel_common/core/middleware.py
fastapi_otel_common/core/models.py
fastapi_otel_common/database/__init__.py
fastapi_otel_common/database/adapters.py
fastapi_otel_common/database/alembic.py
fastapi_otel_common/database/db.py
fastapi_otel_common/logging/__init__.py
fastapi_otel_common/logging/logger.py
fastapi_otel_common/ratelimit/__init__.py
fastapi_otel_common/ratelimit/redis.py
fastapi_otel_common/routes/__init__.py
fastapi_otel_common/routes/health.py
fastapi_otel_common/security/__init__.py
fastapi_otel_common/security/auth.py
fastapi_otel_common/telemetry/__init__.py
fastapi_otel_common/telemetry/tracing.py
fastapi_otel_common-0.1.2.dist-info/licenses/LICENSE
fastapi_otel_common-0.1.2.dist-info/METADATA
fastapi_otel_common-0.1.2.dist-info/WHEEL
fastapi_otel_common-0.1.2.dist-info/top_level.txt
fastapi_otel_common-0.1.2.dist-info/RECORD
