Metadata-Version: 2.4
Name: fastapi_otel_common
Version: 0.1.2
Summary: Production-ready FastAPI components with OpenTelemetry, metrics, health checks, and OIDC integration
Author-email: Ramasubramanian Meenakshisundaram <vinothsubramanian@gmail.com>
License-Expression: MIT
Project-URL: Homepage, https://github.com/devdenvino/fastapi_otel_common
Project-URL: Issues, https://github.com/devdenvino/fastapi_otel_common/issues
Project-URL: Repository, https://github.com/devdenvino/fastapi_otel_common
Project-URL: Documentation, https://github.com/devdenvino/fastapi_otel_common#readme
Keywords: fastapi,opentelemetry,oidc,middleware,security
Classifier: Development Status :: 3 - Alpha
Classifier: Intended Audience :: Developers
Classifier: Programming Language :: Python :: 3
Classifier: Programming Language :: Python :: 3.12
Classifier: Programming Language :: Python :: 3.13
Classifier: Operating System :: OS Independent
Classifier: Framework :: FastAPI
Classifier: Topic :: Software Development :: Libraries :: Python Modules
Classifier: Typing :: Typed
Requires-Python: >=3.12
License-File: LICENSE
Requires-Dist: aiosqlite>=0.20.0
Requires-Dist: alembic>=1.16.5
Requires-Dist: asyncpg>=0.30.0
Requires-Dist: cryptography>=45.0.6
Requires-Dist: fastapi[standard]>=0.116.1
Requires-Dist: httpx>=0.28.1
Requires-Dist: opentelemetry-api>=1.36.0
Requires-Dist: opentelemetry-exporter-jaeger>=1.21.0
Requires-Dist: opentelemetry-exporter-otlp-proto-grpc>=1.15.0
Requires-Dist: opentelemetry-instrumentation-fastapi>=0.57b0
Requires-Dist: opentelemetry-instrumentation-logging>=0.57b0
Requires-Dist: opentelemetry-sdk>=1.36.0
Requires-Dist: psycopg2-binary>=2.9.11
Requires-Dist: psycopg>=3.2.9
Requires-Dist: pyjwt>=2.10.1
Requires-Dist: python-jose>=3.5.0
Requires-Dist: slowapi>=0.1.9
Requires-Dist: sqlalchemy>=2.0.43
Provides-Extra: redis
Requires-Dist: redis>=5.0.0; extra == "redis"
Provides-Extra: mysql
Requires-Dist: aiomysql>=0.2.0; extra == "mysql"
Provides-Extra: dev
Requires-Dist: pytest>=8.0.0; extra == "dev"
Requires-Dist: pytest-asyncio>=0.23.0; extra == "dev"
Requires-Dist: pytest-cov>=4.1.0; extra == "dev"
Requires-Dist: mypy>=1.8.0; extra == "dev"
Requires-Dist: ruff>=0.1.0; extra == "dev"
Requires-Dist: black>=24.0.0; extra == "dev"
Dynamic: license-file
